{
  "_fv": 73,
  "_type": "recipe",
  "definition": {
    "recipeType": "Crafting",
    "recipeRetstackSize": 1,
    "group": "",
    "cookingBookCategory": "MISC",
    "xpReward": 0.0,
    "cookingTime": 200,
    "craftingBookCategory": "MISC",
    "recipeShapeless": false,
    "recipeSlots": [
      {
        "value": "Items.MILK_BUCKET"
      },
      {
        "value": "Items.WHEAT"
      },
      {
        "value": "Items.EGG"
      },
      {
        "value": "Items.APPLE"
      },
      {
        "value": "Items.SUGAR"
      },
      {
        "value": "Items.APPLE"
      },
      {
        "value": "Items.WHEAT"
      },
      {
        "value": "Items.WHEAT"
      },
      {
        "value": "Items.WHEAT"
      }
    ],
    "recipeReturnStack": {
      "value": "CUSTOM:Applepie"
    },
    "name": "applepiecraft",
    "namespace": "mod"
  }
}